py2opsin/__init__.py
py2opsin/opsin-cli-2.8.0-jar-with-dependencies.jar
py2opsin/py2opsin.py
py2opsin-1.1.0.dist-info/LICENSE
py2opsin-1.1.0.dist-info/METADATA
py2opsin-1.1.0.dist-info/WHEEL
py2opsin-1.1.0.dist-info/top_level.txt
py2opsin-1.1.0.dist-info/RECORD
