Metadata-Version: 2.1
Name: py2opsin
Version: 1.1.0
Summary: Simple Python interface to OPSIN: Open Parser for Systematic IUPAC nomenclature
Home-page: https://github.com/JacksonBurns/py2opsin
Author: Jackson Burns, Jonathan Zheng
License: MIT
Classifier: Programming Language :: Python :: 3
Requires-Python: >=3.7
License-File: LICENSE
Requires-Dist: typing-extensions ; python_version < "3.8"
Provides-Extra: dev
Requires-Dist: pubchempy ; extra == 'dev'
Requires-Dist: black ; extra == 'dev'
Requires-Dist: pytest ; extra == 'dev'
Requires-Dist: isort ; extra == 'dev'
